FBA_Matting/__init__.py
FBA_Matting/__main__.py
FBA_Matting/inference.py
FBA_Matting/utils.py
FBA_Matting/networks/__init__.py
FBA_Matting/networks/layers_WS.py
FBA_Matting/networks/models.py
FBA_Matting/networks/resnet_GN_WS.py
FBA_Matting/networks/resnet_bn.py
FBA_Matting/networks/transforms.py
FBA_Matting-1.0.1.dist-info/LICENSE
FBA_Matting-1.0.1.dist-info/METADATA
FBA_Matting-1.0.1.dist-info/WHEEL
FBA_Matting-1.0.1.dist-info/entry_points.txt
FBA_Matting-1.0.1.dist-info/top_level.txt
FBA_Matting-1.0.1.dist-info/RECORD
