Metadata-Version: 2.1
Name: FBA-Matting
Version: 1.0.1
Summary: Image alpha matting
Home-page: https://github.com/MarcoForte/FBA_Matting
Author: Marco Forte and François Pitié
Author-email: ortemarco.irl@gmail.com
License: MIT
Classifier: Development Status :: 5 - Production/Stable
Classifier: Intended Audience :: Developers
Classifier: Intended Audience :: Science/Research
Classifier: Natural Language :: English
Classifier: Operating System :: OS Independent
Classifier: Programming Language :: Python
Classifier: Programming Language :: Python :: 3.5
Classifier: Programming Language :: Python :: 3.6
Classifier: Programming Language :: Python :: 3.7
Classifier: Programming Language :: Python :: 3.8
Classifier: Programming Language :: Python :: 3.9
Classifier: Programming Language :: Python :: 3 :: Only
License-File: LICENSE
Requires-Dist: torch (>=1.4.0)
Requires-Dist: numpy (~=1.24.3)
Requires-Dist: opencv-python (~=4.7.0.72)
Requires-Dist: pillow (~=9.5.0)
